<?xml version="1.0" encoding="UTF-8"?>
<!DOCTYPE auton SYSTEM "auton.dtd">
<auton>


<primitive id = "TRAJECTORY_DRIVE"
choreoname = "BlueLDepotOutpost_A"
time = "3.5"
intakeState = "STATE_INTAKE">
<zone filename = "BlueLaunchZone.xml"/>
</primitive>

<primitive id = "TRAJECTORY_DRIVE"
choreoname = "BlueLDepNO_b"
time = "4.0"
intakeState = "STATE_INTAKE">
<zone filename = "BlueLaunchZone.xml"/>
</primitive>

<primitive id = "DRIVE_STOP_MECH">
<zone filename = "BlueClimbingZone.xml"/>
</primitive>



</auton>